README.txt
setup.py
docs/HISTORY.txt
docs/LICENSE.GPL
docs/LICENSE.txt
valentine/__init__.py
valentine.linguaflow.egg-info/PKG-INFO
valentine.linguaflow.egg-info/SOURCES.txt
valentine.linguaflow.egg-info/dependency_links.txt
valentine.linguaflow.egg-info/entry_points.txt
valentine.linguaflow.egg-info/namespace_packages.txt
valentine.linguaflow.egg-info/not-zip-safe
valentine.linguaflow.egg-info/requires.txt
valentine.linguaflow.egg-info/top_level.txt
valentine/linguaflow/README.txt
valentine/linguaflow/__init__.py
valentine/linguaflow/configure.zcml
valentine/linguaflow/events.py
valentine/linguaflow/overrides.zcml
valentine/linguaflow/patches.py
valentine/linguaflow/plone25.zcml
valentine/linguaflow/setuphandlers.py
valentine/linguaflow/version.txt
valentine/linguaflow/Extensions/Install.py
valentine/linguaflow/browser/__init__.py
valentine/linguaflow/browser/configure.zcml
valentine/linguaflow/browser/portlet.py
valentine/linguaflow/browser/topic.py
valentine/linguaflow/browser/workflow.py
valentine/linguaflow/profiles/default/catalog.xml
valentine/linguaflow/profiles/default/import_steps.xml
valentine/linguaflow/profiles/default/skins.xml
valentine/linguaflow/profiles/default/valentine.linguaflow_various.txt
valentine/linguaflow/profiles/default/workflows.xml
valentine/linguaflow/profiles/default/workflows/linguaflow/definition.xml
valentine/linguaflow/profiles/testing/skins.xml
valentine/linguaflow/profiles/testing/workflows.xml
valentine/linguaflow/profiles/testing/workflows/plone_workflow/definition.xml
valentine/linguaflow/skins/linguaflow_templates/content_status_modify.cpy
valentine/linguaflow/skins/linguaflow_templates/content_status_modify.cpy.metadata
valentine/linguaflow/skins/linguaflow_templates/getDeletableLanguages.py
valentine/linguaflow/skins/linguaflow_templates/global_contentmenu.pt
valentine/linguaflow/skins/linguaflow_templates/manage_translations_form.pt
valentine/linguaflow/skins/linguaflow_templates/portlet_linguaflow.pt
valentine/linguaflow/skins/linguaflow_templates/review_history.pt
valentine/linguaflow/skins/linguaflow_templates/translation_listing.pt
valentine/linguaflow/tests/__init__.py
valentine/linguaflow/tests/base.py
valentine/linguaflow/tests/testing.zcml
valentine/linguaflow/tests/tests.py