Metadata-Version: 1.0
Name: valentine.linguaflow
Version: 0.1
Summary: UNKNOWN
Home-page: http://svn.plone.org/svn/collective/valentine.linguaflow/trunk/
Author: Sasha Vincic
Author-email: sasha dot vincic at valentinewebsystems dot com
License: GPL
Platform: UNKNOWN
Classifier: Programming Language :: Python
Classifier: Topic :: Software Development :: Libraries :: Python Modules
